aletheia/__init__.py
aletheia/aletheia.py
aletheia/cli.py
aletheia/common.py
aletheia/exceptions.py
aletheia/utils.py
aletheia/compat/__init__.py
aletheia/compat/magic.py
aletheia/file_types/__init__.py
aletheia/file_types/base.py
aletheia/file_types/audio/__init__.py
aletheia/file_types/audio/mp3.py
aletheia/file_types/documents/__init__.py
aletheia/file_types/documents/base.py
aletheia/file_types/documents/html.py
aletheia/file_types/documents/json.py
aletheia/file_types/documents/markdown.py
aletheia/file_types/images/__init__.py
aletheia/file_types/images/base.py
aletheia/file_types/images/gif.py
aletheia/file_types/images/jpeg.py
aletheia/file_types/images/png.py
aletheia/file_types/video/__init__.py
aletheia/file_types/video/mkv.py
aletheia/file_types/video/mp4.py
aletheia/file_types/video/webm.py
tests/compat/__init__.py
tests/compat/test_magic.py
tests/file_types/__init__.py
tests/file_types/test_base.py
tests/file_types/audio/__init__.py
tests/file_types/audio/test_mp3.py
tests/file_types/documents/__init__.py
tests/file_types/documents/test_html.py
tests/file_types/documents/test_json.py
tests/file_types/documents/test_markdown.py
tests/file_types/images/__init__.py
tests/file_types/images/test_gif.py
tests/file_types/images/test_jpg.py
tests/file_types/images/test_png.py
tests/file_types/video/__init__.py
tests/file_types/video/test_mkv.py
tests/file_types/video/test_mp4.py
tests/file_types/video/test_webm.py
aletheia-3.3.2.dist-info/LICENSE
aletheia-3.3.2.dist-info/METADATA
aletheia-3.3.2.dist-info/WHEEL
aletheia-3.3.2.dist-info/entry_points.txt
aletheia-3.3.2.dist-info/top_level.txt
aletheia-3.3.2.dist-info/zip-safe
aletheia-3.3.2.dist-info/RECORD
