Metadata-Version: 2.1
Name: aletheia
Version: 3.3.2
Summary: A Python implementation of Aletheia
Home-page: https://danielquinn.github.io/aletheia
Author: Daniel Quinn
Author-email: code@danielquinn.org
Maintainer: Daniel Quinn
Maintainer-email: code@danielquinn.org
License: AGPLv3
Download-URL: https://gitlab.com/danielquinn/aletheia-python
Keywords: command Line,verification,fake news
Platform: UNKNOWN
Classifier: Development Status :: 4 - Beta
Classifier: License :: OSI Approved :: GNU Affero General Public License v3
Classifier: Operating System :: POSIX
Classifier: Operating System :: Unix
Classifier: Programming Language :: Python
Classifier: Programming Language :: Python :: 3.5
Classifier: Programming Language :: Python :: 3.6
Classifier: Programming Language :: Python :: 3.7
Classifier: Programming Language :: Python :: 3.8
Classifier: Programming Language :: Python :: 3.9
Classifier: Programming Language :: Python :: 3.10
Classifier: Programming Language :: Python :: 3 :: Only
Classifier: Topic :: Internet :: WWW/HTTP
License-File: LICENSE
Requires-Dist: cryptography (>=2.1.3)
Requires-Dist: file-magic (>=0.3.0)
Requires-Dist: requests (>=2.18.4)
Requires-Dist: termcolor (>=1.1.0)
Requires-Dist: dnspython (>=1.15.0)
Provides-Extra: doc
Requires-Dist: sphinx ; extra == 'doc'
Requires-Dist: sphinx-rtd-theme ; extra == 'doc'
